<?xml version="1.0"?>
<keyframes>
	<keyframe>
		<name>name</name>
		<start>0.00</start>
		<end>2.00</end>
		<begin>string</begin>
		<complete>string</complete>
	</keyframe>
	<keyframe>
		<name>name</name>
		<start>4.00</start>
		<end>6.00</end>
		<complete>
			<func>
				<name>string</name>
				<params>string</params>
				<scope>string</scope>
			</func>			
		</complete>
	</keyframe>
	<keyframe>
		<name>string</name>
		<start>4.00</start>
		<end>6.00</end>
		<begin>
			<func>loop</func>
			<func>
				<name>string</name>
				<params>string</params>
				<scope>string</scope>
			</func>			
		</begin>
		<complete>
			<func>string</func>
			<func>
				<name>string</name>
				<params>string</params>
				<scope>string</scope>
			</func>			
		</complete>
	</keyframe>
	<keyframe>
		<name>string</name>
		<start>4.00</start>
		<end>6.00</end>
		<begin>
			<func>loop</func>
			<func>
				<name>string</name>
				<params>string</params>
				<scope>string</scope>
			</func>			
		</begin>
	</keyframe>
</keyframes>